tamrof/__init__.py
tamrof-0.0.0.dist-info/LICENSE
tamrof-0.0.0.dist-info/WHEEL
tamrof-0.0.0.dist-info/METADATA
tamrof-0.0.0.dist-info/RECORD
