Metadata-Version: 2.1
Name: tamrof
Version: 0.0.0
Summary: A fast, highly opinionated Python formatter
License: GNU GPL v3
Author: Isaac Harris-Holt
Requires-Python: >=3.10,<4.0
Classifier: License :: Other/Proprietary License
Classifier: Programming Language :: Python :: 3
Classifier: Programming Language :: Python :: 3.10
Classifier: Programming Language :: Python :: 3.11
